odoo8_addon_framework_agreement_department-8.0.2.0.0-py2.7-nspkg.pth
odoo_addons/framework_agreement_department/__openerp__.py
odoo_addons/framework_agreement_department/__init__.py
odoo_addons/framework_agreement_department/README.rst
odoo_addons/framework_agreement_department/view/agreement.xml
odoo_addons/framework_agreement_department/view/portfolio.xml
odoo_addons/framework_agreement_department/model/__init__.py
odoo_addons/framework_agreement_department/model/agreement.py
odoo_addons/framework_agreement_department/model/portfolio.py
odoo8_addon_framework_agreement_department-8.0.2.0.0.dist-info/top_level.txt
odoo8_addon_framework_agreement_department-8.0.2.0.0.dist-info/WHEEL
odoo8_addon_framework_agreement_department-8.0.2.0.0.dist-info/RECORD
odoo8_addon_framework_agreement_department-8.0.2.0.0.dist-info/metadata.json
odoo8_addon_framework_agreement_department-8.0.2.0.0.dist-info/DESCRIPTION.rst
odoo8_addon_framework_agreement_department-8.0.2.0.0.dist-info/METADATA
odoo8_addon_framework_agreement_department-8.0.2.0.0.dist-info/namespace_packages.txt
